setup.py
psb_probability/Binomialdistribution.py
psb_probability/Gaussiandistribution.py
psb_probability/Generaldistribution.py
psb_probability/__init__.py
psb_probability.egg-info/PKG-INFO
psb_probability.egg-info/SOURCES.txt
psb_probability.egg-info/dependency_links.txt
psb_probability.egg-info/not-zip-safe
psb_probability.egg-info/top_level.txt