Metadata-Version: 1.0
Name: psb-probability
Version: 1.2
Summary: Gaussian and Binomial distributions
Home-page: UNKNOWN
Author: Prince Singh Bhadauria
Author-email: princesinghbhadauria@gmail.com
License: UNKNOWN
Platform: UNKNOWN
